kanon/__init__.py
kanon/calendars/__init__.py
kanon/calendars/calendars.py
kanon/conftest.py
kanon/models/__init__.py
kanon/models/meta.py
kanon/models/models.py
kanon/models/table_types.py
kanon/models/utils.py
kanon/py.typed
kanon/tables/__init__.py
kanon/tables/hcolumn.py
kanon/tables/htable.py
kanon/tables/htable_reader.py
kanon/tables/interpolations.py
kanon/tables/symmetries.py
kanon/units/__init__.py
kanon/units/definitions.py
kanon/units/precision.py
kanon/units/radices.py
kanon/utils/__init__.py
kanon/utils/list_to_tuple.py
kanon/utils/looping_list.py
kanon/utils/types/__init__.py
kanon/utils/types/dishas.py
kanon/utils/types/number_types.py
kanon/version.py
kanon-0.6.5.dist-info/LICENSE
kanon-0.6.5.dist-info/WHEEL
kanon-0.6.5.dist-info/METADATA
kanon-0.6.5.dist-info/RECORD
