Metadata-Version: 2.1
Name: kanon
Version: 0.6.5
Summary: History of astronomy library
Home-page: https://dishas.obspm.fr
License: BSD-3-Clause
Keywords: astronomy,history,arithmetic,calendars,ptolemy,sexagesimal
Author: Léni Gauffier
Author-email: lenigauffier@gmail.com
Requires-Python: >=3.8,<4.0
Classifier: Development Status :: 4 - Beta
Classifier: Intended Audience :: Science/Research
Classifier: License :: OSI Approved :: BSD License
Classifier: Operating System :: OS Independent
Classifier: Programming Language :: Python :: 3
Classifier: Programming Language :: Python :: 3.10
Classifier: Programming Language :: Python :: 3.8
Classifier: Programming Language :: Python :: 3.9
Classifier: Topic :: Scientific/Engineering :: Astronomy
Classifier: Topic :: Scientific/Engineering :: Mathematics
Classifier: Topic :: Sociology :: History
Provides-Extra: docs
Provides-Extra: notebook
Requires-Dist: astropy (>=5.0,<6.0)
Requires-Dist: ipykernel (>=6.6.1,<7.0.0); extra == "docs" or extra == "notebook"
Requires-Dist: ipython (>=8.0.0,<9.0.0); extra == "docs" or extra == "notebook"
Requires-Dist: matplotlib (>=3.5.1,<4.0.0)
Requires-Dist: nbformat (>=5.1.3,<6.0.0); extra == "notebook"
Requires-Dist: nbsphinx (>=0.8.8,<0.9.0); extra == "docs"
Requires-Dist: numpy (>=1.22.0,<2.0.0)
Requires-Dist: pandas (>=1.3.5,<2.0.0)
Requires-Dist: papermill (>=2.3.3,<3.0.0); extra == "docs" or extra == "notebook"
Requires-Dist: requests (>=2.27.1,<3.0.0)
Requires-Dist: scipy (>=1.7.3,<2.0.0); python_version >= "3.8" and python_version < "3.11"
Requires-Dist: sphinx-astropy (>=1.7.0,<2.0.0); extra == "docs"
Requires-Dist: sphinx-rtd-theme (>=1.0.0,<2.0.0); extra == "docs"
Project-URL: Repository, https://github.com/legau/kanon
